odoo/addons/account_payment_show_invoice/README.rst
odoo/addons/account_payment_show_invoice/__init__.py
odoo/addons/account_payment_show_invoice/__manifest__.py
odoo/addons/account_payment_show_invoice/i18n/account_payment_show_invoice.pot
odoo/addons/account_payment_show_invoice/models/__init__.py
odoo/addons/account_payment_show_invoice/models/account_payment.py
odoo/addons/account_payment_show_invoice/readme/CONTRIBUTORS.rst
odoo/addons/account_payment_show_invoice/readme/DESCRIPTION.rst
odoo/addons/account_payment_show_invoice/readme/USAGE.rst
odoo/addons/account_payment_show_invoice/static/description/icon.png
odoo/addons/account_payment_show_invoice/static/description/index.html
odoo/addons/account_payment_show_invoice/tests/__init__.py
odoo/addons/account_payment_show_invoice/tests/test_payment_ref_invoice.py
odoo/addons/account_payment_show_invoice/views/account_payment_view.xml
odoo12_addon_account_payment_show_invoice-12.0.1.0.1.dist-info/METADATA
odoo12_addon_account_payment_show_invoice-12.0.1.0.1.dist-info/WHEEL
odoo12_addon_account_payment_show_invoice-12.0.1.0.1.dist-info/top_level.txt
odoo12_addon_account_payment_show_invoice-12.0.1.0.1.dist-info/RECORD
